socket_plotter/__init__.py
socket_plotter/api.py
socket_plotter/app/__init__.py
socket_plotter/app/imageplotter.py
socket_plotter/app/lineplotter.py
socket_plotter/app/receiver.py
socket_plotter-0.1.4.dist-info/LICENSE
socket_plotter-0.1.4.dist-info/METADATA
socket_plotter-0.1.4.dist-info/WHEEL
socket_plotter-0.1.4.dist-info/entry_points.txt
socket_plotter-0.1.4.dist-info/top_level.txt
socket_plotter-0.1.4.dist-info/RECORD
