Metadata-Version: 2.1
Name: socket-plotter
Version: 0.1.4
Summary: A simple live plotter via socket.
Home-page: https://github.com/KosukeMizuno/socket-plotter
License: MIT
Platform: UNKNOWN
Classifier: Programming Language :: Python :: 3
Requires-Dist: pyqtgraph
Requires-Dist: numpy
Provides-Extra: dev
Requires-Dist: PySide2 ; extra == 'dev'
Requires-Dist: black ; extra == 'dev'
Requires-Dist: flake8 ; extra == 'dev'
Requires-Dist: flake8-print ; extra == 'dev'
Requires-Dist: darglint ; extra == 'dev'
Provides-Extra: pyside
Requires-Dist: PySide2 ; extra == 'pyside'
